detail/__init__.py
detail/cli.py
detail/core.py
detail/exceptions.py
detail/github.py
detail/tests/__init__.py
detail/tests/test_cli.py
detail/tests/test_core.py
detail/tests/test_github.py
detail/tests/test_integration.py
detail/tests/test_utils.py
detail/tests/test_version.py
detail/utils.py
detail/version.py
detail-0.3.0.dist-info/LICENSE
detail-0.3.0.dist-info/METADATA
detail-0.3.0.dist-info/WHEEL
detail-0.3.0.dist-info/entry_points.txt
detail-0.3.0.dist-info/RECORD
